LICENSE
README.md
setup.py
pyhigh/__init__.py
pyhigh/download.py
pyhigh/elevation.py
pyhigh/hgt.py
pyhigh/pyhigh.py
pyhigh/unzip.py
pyhigh.egg-info/PKG-INFO
pyhigh.egg-info/SOURCES.txt
pyhigh.egg-info/dependency_links.txt
pyhigh.egg-info/entry_points.txt
pyhigh.egg-info/not-zip-safe
pyhigh.egg-info/requires.txt
pyhigh.egg-info/top_level.txt
tests/test_pyhigh.py