Metadata-Version: 2.1
Name: pyhigh
Version: 0.0.6
Summary: Python library to get elevation data
Home-page: https://github.com/sgherbst/pyhigh
Download-URL: https://github.com/sgherbst/pyhigh/archive/v0.0.6.tar.gz
Author: Steven Herbst
Author-email: sherbst@stanford.edu
License: MIT
Keywords: elevation
Classifier: Development Status :: 3 - Alpha
Classifier: License :: OSI Approved :: MIT License
Classifier: Programming Language :: Python :: 3.7
Requires-Python: >=3.7
License-File: LICENSE
Requires-Dist: numpy
Requires-Dist: requests
